mightyzap_17lf/__init__.py
mightyzap_17lf/__main__.py
mightyzap_17lf-0.1.0.dist-info/METADATA
mightyzap_17lf-0.1.0.dist-info/WHEEL
mightyzap_17lf-0.1.0.dist-info/entry_points.txt
mightyzap_17lf-0.1.0.dist-info/top_level.txt
mightyzap_17lf-0.1.0.dist-info/RECORD
